<?xml version='1.0' encoding='utf-8' standalone='yes' ?>
<map>
    <boolean name="Hide_div" value="true" />
    <int name="ModChatLeftBubble" value="-14168651" />
    <int name="BGColor" value="-14735063" />
    <boolean name="yo_hideinfo" value="false" />
    <boolean name="custom_wall" value="false" />
    <int name="quoted_bg_picker" value="-15022421" />
    <int name="ModChatDarkColor" value="-14735063" />
    <string name="tick_style">nlmod2</string>
    <int name="ModFabNormalColor" value="-14168651" />
    <string name="yo_nicons">0</string>
    <int name="ModChaSendBKColor" value="-685322827" />
    <boolean name="my_name" value="false" />
    <int name="ModConColor" value="-14735063" />
    <int name="ModChatRightBubble" value="-14735063" />
    <int name="date_divider_color_picker" value="-14735063" />
    <int name="ModChatTextColor" value="-14168651" />
    <boolean name="my_statusd" value="false" />
    <boolean name="chats_show_contact_online_toast_check" value="false" />
    <string name="ConvoEntry">12</string>
    <string name="font">Default</string>
    <boolean name="onlinechat" value="false" />
    <int name="ModChatBubbleText" value="-1052689" />
    <int name="ModlastseenColor" value="-1052689" />
    <boolean name="PicProf" value="true" />
    <boolean name="hide_action_l" value="false" />
    <int name="emojipopup_header" value="-14735063" />
    <boolean name="log_show_name_check" value="true" />
    <int name="text_size_pick" value="15" />
    <int name="quoted_name_picker" value="-2434342" />
    <boolean name="hide_action_m" value="false" />
    <int name="date_left_color" value="-14735063" />
    <boolean name="Conv_call_btn" value="true" />
    <int name="ModChaSendColor" value="-14735063" />
    <string name="bubble_style">ed</string>
    <int name="ModFabTextColor" value="-14735063" />
    <int name="main_text" value="15" />
    <int name="ModOnlineColor" value="-1052689" />
    <int name="HomeBarText" value="-14168651" />
    <int name="ModChatBubbleTextLeft" value="-14735063" />
    <int name="emojipopup_icons" value="-14168651" />
    <int name="quoted_divider_picker" value="-2434342" />
    <int name="date_right_color" value="-2434342" />
    <boolean name="hide_fab" value="false" />
    <boolean name="start_bl" value="false" />
    <boolean name="statuschat" value="true" />
    <int name="square_photo_ratio_picker" value="100" />
    <int name="ModChatEntry" value="-14735063" />
    <boolean name="Archv_chats" value="false" />
    <int name="ModDarkConPickColorNav" value="-14735063" />
    <int name="ModFabBgColor" value="1427687083" />
    <int name="ModConBackColor" value="-14735063" />
    <int name="quoted_text_picker" value="-2434342" />
    <int name="emojipopup_body" value="-14735063" />
    <int name="ModConDarkColor" value="-14735063" />
    <boolean name="TxtSelect" value="true" />
    <boolean name="custom_wall_profilepic" value="false" />
    <boolean name="enable_old" value="false" />
    <int name="ModConTextColor" value="-14168651" />
    <int name="date_bubble_color_picker" value="-14168651" />
    <int name="HomeCounterBK" value="-14168651" />
    <int name="ModFabPressedColor" value="-15022421" />
    <boolean name="hide_action_a" value="false" />
    <int name="ModChatEmojiColor" value="-14168651" />
    <string name="HomeEntry">wamod</string>
    <int name="ModDarkConPickColor" value="-14735063" />
    <boolean name="hide_action_b" value="false" />
    <int name="ModConPickColor" value="-14735063" />
    <boolean name="elapsed_time" value="true" />
    <int name="ModChatBtnColor" value="-14168651" />
    <int name="ModConPickBackColor" value="-14735063" />
    <int name="row_resizer" value="0" />
    <boolean name="AttBt" value="false" />
    <int name="ModChatColor" value="-14735063" />
</map>
