<?xml version='1.0' encoding='utf-8' standalone='yes' ?>
<map>
    <boolean name="Hide_div" value="false" />
    <boolean name="ModConBackColor_Gactive" value="false" />
    <int name="ModChatLeftBubble" value="-2648161" />
    <boolean name="ModlastseenColor_Gactive" value="false" />
    <boolean name="yo_hideinfo" value="false" />
    <boolean name="date_left_color_Gactive" value="false" />
    <boolean name="custom_wall" value="false" />
    <int name="ModChatDarkColor" value="-199187" />
    <int name="ModChaSendBKColor" value="-2648161" />
    <boolean name="ModChatGStatusT_Gactive" value="false" />
    <int name="ModConColor" value="-199187" />
    <int name="pic_chat_size_picker" value="60" />
    <boolean name="emojipopup_icons_Gactive" value="false" />
    <int name="ModChatBubbleText" value="-2648161" />
    <int name="ModlastseenColor" value="-2648161" />
    <boolean name="PicProf" value="false" />
    <int name="emojipopup_header" value="-2648161" />
    <int name="ModChatColor_GCDir" value="1" />
    <boolean name="date_right_color_Gactive" value="false" />
    <boolean name="statuses_bar_text_picker_Gactive" value="false" />
    <int name="ModConColor_GC" value="-2648161" />
    <int name="quoted_name_picker" value="-2648161" />
    <boolean name="participant_name_color_picker_Gactive" value="false" />
    <boolean name="Conv_call_btn" value="false" />
    <boolean name="quoted_name_picker_Gactive" value="false" />
    <int name="ModChatGStatusB_GCDir" value="0" />
    <int name="ModFabTextColor" value="-11578825" />
    <int name="main_text" value="16" />
    <int name="ModChatBubbleTextLeft" value="-199187" />
    <int name="statuses_bar_bg_picker_GC" value="-5790072" />
    <int name="emojipopup_icons" value="-199187" />
    <int name="ModChatGStatusB_GC" value="-199187" />
    <int name="quoted_divider_picker" value="-11578825" />
    <int name="date_right_color" value="-2648161" />
    <int name="statuses_bar_bg_picker" value="-199187" />
    <boolean name="ModFabNormalColor_Gactive" value="false" />
    <boolean name="statuschat" value="false" />
    <int name="ModChatEntry" value="-199187" />
    <boolean name="Archv_chats" value="false" />
    <int name="pagetitle_picker" value="-2648161" />
    <boolean name="pagetitle_picker_Gactive" value="false" />
    <boolean name="ModDarkConPickColor_Gactive" value="false" />
    <int name="ModConBackColor" value="-199187" />
    <boolean name="ModChatTextColor_Gactive" value="false" />
    <boolean name="group_mypic" value="true" />
    <boolean name="ModOnlineColor_Gactive" value="false" />
    <int name="quoted_text_picker" value="-11578825" />
    <boolean name="emojipopup_header_Gactive" value="false" />
    <int name="tabindicator" value="-11578825" />
    <boolean name="custom_wall_profilepic" value="false" />
    <boolean name="chats_date_pending_color_picker_Gactive" value="false" />
    <int name="ModConColor_GCDir" value="1" />
    <boolean name="ModFabTextColor_Gactive" value="false" />
    <string name="convostyle">1</string>
    <boolean name="ModFabPressedColor_Gactive" value="false" />
    <boolean name="statuses_bar_bg_picker_Gactive" value="true" />
    <boolean name="ModChaSendBKColor_Gactive" value="false" />
    <boolean name="ModChatLeftBubble_Gactive" value="false" />
    <boolean name="HomeBarText_Gactive" value="false" />
    <boolean name="hide_action_b" value="false" />
    <boolean name="ModChatColor_Gactive" value="false" />
    <boolean name="elapsed_time" value="false" />
    <int name="ModChatBtnColor" value="-2648161" />
    <int name="ModChatColor" value="-199187" />
    <boolean name="quoted_bg_picker_Gactive" value="false" />
    <int name="ModConPickColor_GCDir" value="1" />
    <int name="BGColor" value="-1" />
    <boolean name="emojipopup_body_Gactive" value="false" />
    <int name="ModContactNameColor" value="-2648161" />
    <boolean name="NameProf" value="false" />
    <string name="tick_style">yousef</string>
    <int name="quoted_bg_picker" value="-199187" />
    <int name="ModChatGStatusB" value="-2648161" />
    <int name="ModFabNormalColor" value="-2648161" />
    <boolean name="ModChatEntry_Gactive" value="false" />
    <boolean name="my_name" value="true" />
    <boolean name="ModConColor_Gactive" value="false" />
    <boolean name="ModChatBtnColor_Gactive" value="false" />
    <int name="ModChatRightBubble" value="-199187" />
    <int name="statuses_bar_bg_picker_GCDir" value="3" />
    <int name="ModChatTextColor" value="-2648161" />
    <boolean name="my_statusd" value="false" />
    <boolean name="chats_show_contact_online_toast_check" value="false" />
    <string name="font">Default</string>
    <string name="ConvoEntry">7</string>
    <int name="ModConPickColor_GC" value="-2648161" />
    <boolean name="onlinechat" value="false" />
    <boolean name="ModChatBubbleTextLeft_Gactive" value="false" />
    <boolean name="ModChatBubbleText_Gactive" value="false" />
    <boolean name="ModConPickColor_Gactive" value="false" />
    <boolean name="hide_action_l" value="false" />
    <boolean name="chat_contactpic" value="true" />
    <int name="participant_name_color_picker" value="-199187" />
    <boolean name="log_show_name_check" value="true" />
    <int name="chats_row_divider_picker" value="-11578825" />
    <int name="text_size_pick" value="16" />
    <boolean name="ModChatGStatusB_Gactive" value="true" />
    <boolean name="ModChaSendColor_Gactive" value="false" />
    <int name="chats_date_pending_color_picker" value="-11578825" />
    <int name="ModConBackColor_GC" value="-2648161" />
    <boolean name="hide_action_m" value="false" />
    <int name="date_left_color" value="-199187" />
    <int name="chats_date_color_picker" value="-258" />
    <int name="ModChaSendColor" value="-199187" />
    <string name="bubble_style">d3</string>
    <int name="pagetitle_sel_picker" value="-11578825" />
    <int name="ModOnlineColor" value="-2648161" />
    <int name="HomeBarText" value="-2648161" />
    <boolean name="hide_fab" value="false" />
    <int name="square_photo_ratio_picker" value="100" />
    <boolean name="ModConTextColor_Gactive" value="false" />
    <boolean name="chat_mypic" value="true" />
    <boolean name="ModChatRightBubble_Gactive" value="false" />
    <int name="emojipopup_body" value="-199187" />
    <int name="ModConDarkColor" value="-199187" />
    <boolean name="TxtSelect" value="true" />
    <boolean name="tabindicator_Gactive" value="false" />
    <int name="statuses_bar_text_picker" value="-258" />
    <int name="ModConBackColor_GCDir" value="2" />
    <int name="ModConTextColor" value="-2648161" />
    <int name="ModChatGStatusT" value="-11578825" />
    <boolean name="ModContactNameColor_Gactive" value="false" />
    <boolean name="group_participants_pic" value="true" />
    <int name="ModFabPressedColor" value="-199187" />
    <boolean name="hide_action_a" value="false" />
    <int name="ModChatEmojiColor" value="-2648161" />
    <boolean name="chats_row_divider_picker_Gactive" value="false" />
    <int name="ModDarkConPickColor" value="-199187" />
    <string name="HomeEntry">yousef</string>
    <int name="ModConPickColor" value="-199187" />
    <boolean name="quoted_divider_picker_Gactive" value="false" />
    <boolean name="pagetitle_sel_picker_Gactive" value="false" />
    <boolean name="chats_date_color_picker_Gactive" value="false" />
    <int name="ModChatColor_GC" value="-2648161" />
    <boolean name="quoted_text_picker_Gactive" value="false" />
    <boolean name="AttBt" value="false" />
    <boolean name="ModChatEmojiColor_Gactive" value="false" />
</map>
