<?xml version='1.0' encoding='utf-8' standalone='yes' ?>
<map>
    <boolean name="tabadgeBKColor_Gactive" value="false" />
    <boolean name="Hide_div" value="false" />
    <boolean name="rcEmojiColor_Gactive" value="false" />
    <int name="ModChatLeftBubble" value="-25612" />
    <boolean name="ModlastseenColor_Gactive" value="false" />
    <boolean name="yo_hideinfo" value="false" />
    <boolean name="custom_wall" value="false" />
    <boolean name="date_left_color_Gactive" value="false" />
    <int name="rcAddColor" value="-25612" />
    <int name="ModChatDarkColor" value="-2916097" />
    <string name="yo_nicons">0</string>
    <int name="ModChaSendBKColor" value="-9499291" />
    <boolean name="ModChatGStatusT_Gactive" value="false" />
    <int name="ModConColor" value="-6068323" />
    <boolean name="date_divider_color_picker_Gactive" value="false" />
    <int name="rcname_color" value="-9499291" />
    <int name="ConvoBack" value="-25612" />
    <boolean name="emojipopup_icons_Gactive" value="false" />
    <int name="btn_voice_color_chat_picker" value="-2916097" />
    <int name="ModChatBubbleText" value="-220933" />
    <boolean name="rc_Txunseen_Gactive" value="false" />
    <int name="ModlastseenColor" value="-25612" />
    <int name="tabadgeTextColor" value="-25612" />
    <boolean name="PicProf" value="false" />
    <int name="emojipopup_header" value="-220933" />
    <int name="tabadgeBKColor" value="-9499291" />
    <boolean name="date_right_color_Gactive" value="false" />
    <boolean name="statuses_bar_text_picker_Gactive" value="false" />
    <int name="rc_Txunseen" value="-9499291" />
    <int name="quoted_name_picker" value="-9499291" />
    <boolean name="participant_name_color_picker_Gactive" value="false" />
    <boolean name="Conv_call_btn" value="false" />
    <boolean name="quoted_name_picker_Gactive" value="false" />
    <boolean name="seekbar_color_chat_picker_Gactive" value="false" />
    <boolean name="rc_Bkunseen_Gactive" value="false" />
    <int name="rcMicColor" value="-25612" />
    <boolean name="tabadgeTextColor_Gactive" value="false" />
    <int name="main_text" value="17" />
    <int name="ModChatBubbleTextLeft" value="-9499291" />
    <int name="emojipopup_icons" value="-6068323" />
    <int name="quoted_divider_picker" value="-25612" />
    <int name="date_right_color" value="-9499291" />
    <int name="statuses_bar_bg_picker" value="-9499291" />
    <boolean name="start_bl" value="false" />
    <boolean name="statuschat" value="true" />
    <int name="mention_color_chat_picker" value="-9499291" />
    <int name="ModChatEntry" value="-9499291" />
    <boolean name="Archv_chats" value="false" />
    <int name="pagetitle_picker" value="-9499291" />
    <int name="ModDarkConPickColorNav" value="-6068323" />
    <boolean name="pagetitle_picker_Gactive" value="false" />
    <boolean name="chat_contactpicV2" value="false" />
    <int name="rcText" value="-9499291" />
    <boolean name="ModDarkConPickColor_Gactive" value="false" />
    <boolean name="pic_inside" value="false" />
    <boolean name="ModChatTextColor_Gactive" value="false" />
    <boolean name="ModOnlineColor_Gactive" value="false" />
    <int name="quoted_text_picker" value="-25612" />
    <boolean name="rc_emox_Gactive" value="false" />
    <boolean name="emojipopup_header_Gactive" value="false" />
    <boolean name="custom_wall_profilepic" value="false" />
    <boolean name="mention_color_chat_picker_Gactive" value="false" />
    <boolean name="btn_voice_color_chat_picker_Gactive" value="false" />
    <int name="tabindicator" value="-16777216" />
    <int name="rc_Bkunseen" value="-6068323" />
    <int name="ModChatBubbleHyperlinks" value="-6068323" />
    <int name="date_bubble_color_picker" value="-9499291" />
    <int name="HomeCounterBK" value="-6068323" />
    <string name="convostyle">0</string>
    <boolean name="ModChatBubbleHyperlinks_Gactive" value="false" />
    <boolean name="statuses_bar_bg_picker_Gactive" value="false" />
    <string name="conversation_style_attach">0</string>
    <boolean name="ModChaSendBKColor_Gactive" value="false" />
    <boolean name="date_bubble_color_picker_Gactive" value="false" />
    <boolean name="ModChatLeftBubble_Gactive" value="false" />
    <boolean name="HomeBarText_Gactive" value="false" />
    <boolean name="hide_action_b" value="false" />
    <boolean name="ModChatColor_Gactive" value="false" />
    <boolean name="elapsed_time" value="false" />
    <int name="ModChatBtnColor" value="-6068323" />
    <int name="ModChatColor" value="-6068323" />
    <int name="rcChatsColor" value="-6068323" />
    <boolean name="quoted_bg_picker_Gactive" value="false" />
    <int name="BGColor" value="-6068323" />
    <boolean name="emojipopup_body_Gactive" value="false" />
    <boolean name="NameProf" value="false" />
    <int name="ModContactNameColor" value="-6068323" />
    <boolean name="home_imgBK" value="true" />
    <int name="pic_chat_size_pickerV2" value="40" />
    <string name="tick_style">rcios11</string>
    <int name="quoted_bg_picker" value="-6068323" />
    <string name="pic_startlocation">1</string>
    <int name="ModChatGStatusB" value="-6068323" />
    <boolean name="ModChatEntry_Gactive" value="false" />
    <boolean name="chat_icon_forward_picker_Gactive" value="false" />
    <boolean name="my_name" value="true" />
    <boolean name="HomeCounterText_Gactive" value="false" />
    <boolean name="ModChatBtnColor_Gactive" value="false" />
    <boolean name="ModConColor_Gactive" value="false" />
    <int name="ModChatRightBubble" value="-6068323" />
    <int name="date_divider_color_picker" value="-6068323" />
    <int name="ModChatTextColor" value="-25612" />
    <string name="ConvoEntry">5</string>
    <string name="font">Satisfy</string>
    <boolean name="chats_show_contact_online_toast_check" value="false" />
    <boolean name="my_statusd" value="false" />
    <boolean name="onlinechat" value="false" />
    <boolean name="ModChatBubbleTextLeft_Gactive" value="false" />
    <boolean name="hide_action_l" value="false" />
    <int name="participant_name_color_picker" value="-2916097" />
    <boolean name="ModChatBubbleText_Gactive" value="false" />
    <boolean name="ModConPickColor_Gactive" value="false" />
    <boolean name="log_show_name_check" value="true" />
    <boolean name="group_mypicV2" value="false" />
    <int name="chats_row_divider_picker" value="-2916097" />
    <boolean name="rcname_color_Gactive" value="false" />
    <int name="text_size_pick" value="16" />
    <boolean name="ModChatGStatusB_Gactive" value="false" />
    <boolean name="ModChaSendColor_Gactive" value="false" />
    <boolean name="hide_action_m" value="false" />
    <int name="date_left_color" value="-6068323" />
    <string name="home">0</string>
    <int name="ModChaSendColor" value="-25612" />
    <boolean name="ConvoBack_Gactive" value="false" />
    <boolean name="enable_o1d" value="false" />
    <string name="bubble_style">wapaper</string>
    <int name="HomeCounterText" value="-9499291" />
    <int name="ModOnlineColor" value="-25612" />
    <int name="pagetitle_sel_picker" value="-9499291" />
    <boolean name="rcAddColor_Gactive" value="false" />
    <int name="HomeBarText" value="-9499291" />
    <boolean name="hide_fab" value="true" />
    <int name="seekbar_color_chat_picker" value="-9499291" />
    <int name="square_photo_ratio_picker" value="100" />
    <boolean name="HomeCounterBK_Gactive" value="false" />
    <int name="rc_emox" value="-25612" />
    <boolean name="ModConTextColor_Gactive" value="false" />
    <boolean name="rcChatsColor_Gactive" value="false" />
    <boolean name="ModChatRightBubble_Gactive" value="false" />
    <int name="emojipopup_body" value="-25612" />
    <boolean name="group_participants_picV2" value="true" />
    <int name="ModConDarkColor" value="-2916097" />
    <boolean name="TxtSelect" value="true" />
    <int name="statuses_bar_text_picker" value="-25612" />
    <boolean name="tabindicator_Gactive" value="false" />
    <boolean name="chat_mypicV2" value="false" />
    <int name="rcEmojiColor" value="-25612" />
    <int name="ModChatGStatusT" value="-9499291" />
    <int name="ModConTextColor" value="-9499291" />
    <boolean name="rcText_Gactive" value="false" />
    <int name="chat_icon_forward_picker" value="-220933" />
    <boolean name="ModContactNameColor_Gactive" value="false" />
    <boolean name="rcMicColor_Gactive" value="false" />
    <boolean name="BGColor_Gactive" value="false" />
    <boolean name="hide_action_a" value="false" />
    <boolean name="chats_row_divider_picker_Gactive" value="false" />
    <string name="HomeEntry">yousef</string>
    <int name="ModDarkConPickColor" value="-6068323" />
    <boolean name="ModDarkConPickColorNav_Gactive" value="false" />
    <int name="ModConPickColor" value="-6068323" />
    <boolean name="quoted_divider_picker_Gactive" value="false" />
    <boolean name="pagetitle_sel_picker_Gactive" value="false" />
    <boolean name="quoted_text_picker_Gactive" value="false" />
    <boolean name="AttBt" value="false" />
    <int name="row_resizer" value="0" />
</map>
