<?xml version='1.0' encoding='utf-8' standalone='yes' ?>
<map>
    <int name="ModChatBubbleText" value="-503316481" />
    <int name="ModChaSendBKColor" value="-501798354" />
    <int name="quoted_text_picker" value="-1" />
    <boolean name="my_statusd" value="false" />
    <int name="emojipopup_icons" value="-1" />
    <boolean name="ModContactNameColor_Gactive" value="false" />
    <boolean name="quoted_bg_picker_Gactive" value="false" />
    <boolean name="date_bubble_color_picker_Gactive" value="false" />
    <int name="ModFabNormalColor" value="-501798354" />
    <boolean name="hide_action_l" value="false" />
    <int name="ModContactNameColor" value="-1" />
    <boolean name="hide_action_m" value="false" />
    <boolean name="Conv_call_btn" value="false" />
    <boolean name="ModFabTextColor_Gactive" value="false" />
    <boolean name="Hide_div" value="true" />
    <boolean name="BGColor_Gactive" value="false" />
    <int name="ModConDarkColor" value="-15790578" />
    <int name="date_right_color" value="-889192449" />
    <int name="emojipopup_body" value="-501798354" />
    <boolean name="ModChatEmojiColor_Gactive" value="false" />
    <boolean name="emojipopup_body_Gactive" value="false" />
    <boolean name="ModChatBtnColor_Gactive" value="false" />
    <int name="ModChatRightBubble" value="-501798354" />
    <boolean name="onlinechat" value="false" />
    <int name="ModChatLeftBubble" value="-1567942593" />
    <boolean name="ModChaSendBKColor_Gactive" value="false" />
    <boolean name="start_bl" value="false" />
    <string name="convostyle">1</string>
    <int name="HomeCounterBK" value="-7661505" />
    <int name="ModChatBubbleTextLeft" value="-419430401" />
    <int name="ModDarkConPickColor" value="-149476818" />
    <boolean name="Archv_chats" value="false" />
    <int name="ModFabTextColor" value="-1" />
    <int name="ModConTextColor" value="-1" />
    <boolean name="ModConTextColor_Gactive" value="false" />
    <boolean name="ModOnlineColor_Gactive" value="false" />
    <boolean name="yo_hideinfo" value="false" />
    <boolean name="PicProf" value="false" />
    <boolean name="date_divider_color_picker_Gactive" value="false" />
    <int name="HomeCounterText" value="-67108865" />
    <boolean name="btn_voice_color_chat_picker_Gactive" value="false" />
    <boolean name="ModChatColor_Gactive" value="false" />
    <string name="bubble_style">ios11</string>
    <int name="ModChatBtnColor" value="-863299521" />
    <int name="ModChatBubbleHyperlinks" value="-16734465" />
    <int name="ModlastseenColor" value="-1" />
    <boolean name="ModChatLeftBubble_Gactive" value="false" />
    <int name="ModDarkConPickColorNav" value="-501798354" />
    <boolean name="AttBt" value="false" />
    <int name="BGColor" value="-863299521" />
    <boolean name="HomeCounterText_Gactive" value="false" />
    <string name="font">Bariol</string>
    <int name="date_left_color" value="-503316481" />
    <int name="quoted_bg_picker" value="-863299521" />
    <boolean name="ModDarkConPickColor_Gactive" value="false" />
    <boolean name="ModChatBubbleText_Gactive" value="false" />
    <int name="date_bubble_color_picker" value="-501798354" />
    <int name="seekbar_color_chat_picker" value="-443869121" />
    <int name="statuses_bar_bg_picker" value="-149476818" />
    <boolean name="ModChaSendColor_Gactive" value="false" />
    <int name="ModChatEmojiColor" value="-863299521" />
    <int name="ModChaSendColor" value="-863299521" />
    <int name="emojipopup_header" value="-501798354" />
    <boolean name="emojipopup_icons_Gactive" value="false" />
    <boolean name="ModDarkConPickColorNav_Gactive" value="false" />
    <int name="ModChatColor" value="-149476818" />
    <boolean name="log_show_name_check" value="true" />
    <boolean name="emojipopup_header_Gactive" value="false" />
    <boolean name="HomeCounterBK_Gactive" value="false" />
    <boolean name="home_imgBK" value="true" />
    <string name="yo_nicons">0</string>
    <int name="statuses_bar_text_picker" value="-1" />
    <int name="row_resizer" value="0" />
    <boolean name="seekbar_color_chat_picker_Gactive" value="false" />
    <int name="ModConPickColor" value="-149476818" />
    <boolean name="date_right_color_Gactive" value="false" />
    <boolean name="enable_old" value="false" />
    <string name="ConvoEntry">7</string>
    <int name="ModConColor" value="-443869121" />
    <boolean name="chats_show_contact_online_toast_check" value="true" />
    <string name="tick_style">rcios11</string>
    <boolean name="hide_fab" value="false" />
    <boolean name="date_left_color_Gactive" value="false" />
    <boolean name="ModChatTextColor_Gactive" value="false" />
    <boolean name="my_name" value="false" />
    <boolean name="ModChatBubbleTextLeft_Gactive" value="false" />
    <boolean name="ModChatEntry_Gactive" value="false" />
    <int name="ModChatDarkColor" value="-15790578" />
    <boolean name="elapsed_time" value="false" />
    <int name="btn_voice_color_chat_picker" value="-443869121" />
    <boolean name="ModlastseenColor_Gactive" value="false" />
    <boolean name="ModFabNormalColor_Gactive" value="false" />
    <boolean name="hide_action_a" value="true" />
    <int name="ModChatEntry" value="-938005970" />
    <boolean name="hide_action_b" value="true" />
    <int name="square_photo_ratio_picker" value="100" />
    <boolean name="statuses_bar_bg_picker_Gactive" value="false" />
    <int name="ModChatTextColor" value="-503316481" />
    <boolean name="quoted_text_picker_Gactive" value="false" />
    <boolean name="ModConPickColor_Gactive" value="false" />
    <string name="HomeEntry">yousef</string>
    <boolean name="ModChatBubbleHyperlinks_Gactive" value="false" />
    <boolean name="statuses_bar_text_picker_Gactive" value="false" />
    <int name="date_divider_color_picker" value="-443869121" />
    <int name="main_text" value="17" />
    <boolean name="ModChatRightBubble_Gactive" value="false" />
    <boolean name="ModConColor_Gactive" value="false" />
    <int name="text_size_pick" value="16" />
    <int name="ModOnlineColor" value="-7661505" />
</map>
